{
  "questionId": "820d7a73-s1",
  "originalId": "820d7a73",
  "setId": "set-1",
  "section": "Math",
  "difficulty": "Easy",
  "difficultyCode": "E",
  "domain": "Problem-Solving and Data Analysis",
  "domainCode": "Q",
  "skill": "One-variable data: Distributions and measures of center and spread",
  "skillCode": "Q.C.",
  "type": "spr",
  "stimulus": null,
  "stem": "<p>The table shows the distribution of 280 books collected by 7 different classes for a book drive.</p><table border=\"1\" cellpadding=\"6\" style=\"border-collapse: collapse; margin: 0 auto;\"><tr><th>Class</th><th>1</th><th>2</th><th>3</th><th>4</th><th>5</th><th>6</th><th>7</th></tr><tr><td>Books</td><td>30</td><td>50</td><td>35</td><td>45</td><td>55</td><td>25</td><td>40</td></tr></table><p>How many books were collected by class 5?</p>",
  "answerOptions": null,
  "keys": [
    "55"
  ],
  "rationale": "<p>The correct answer is <strong>55</strong>. According to the table, class 5 collected 55 books.</p>",
  "generatedAt": "2026-05-26T00:21:36Z",
  "templateId": "one-variable-data-distributions-and-measures-of-center-and-spread.A3.T6.easy"
}