{
  "total_clones": 2767,
  "tagged_now": 2279,
  "already_tagged": 0,
  "untagged": 488,
  "untagged_ids_sample": [
    "a5aee181",
    "902dc959",
    "13d9a1c3",
    "bf8d843e",
    "6676f055",
    "911383f2",
    "99269e03",
    "364a2d25",
    "0980fcdd",
    "78d5f91a",
    "652054da",
    "f28944ff",
    "fcdf87b7",
    "100030d9",
    "95ed0b69",
    "b3b07f0c",
    "52e589f9",
    "4e18fc5d",
    "6e02cd78",
    "95d1c344",
    "dc77e0dc",
    "a267bd29",
    "a1262cdb",
    "ff2c1431",
    "f1fa0821",
    "87a3de81",
    "a4f61d75",
    "44076c7d",
    "70ebd3d0",
    "e24765e6",
    "38525983",
    "ad7dbb22",
    "9bb4107c",
    "8e2e424e",
    "7e6c745f",
    "f5929f7a",
    "4e400635",
    "5e422ff9",
    "a5834ea4",
    "a04190b7",
    "c651cc56",
    "41fdc0b8",
    "53487897",
    "19fdf387",
    "d62ad380",
    "cb8f449f",
    "6ba39da5",
    "868fc236",
    "c5082ce3",
    "b544a348"
  ],
  "skill_distribution": {
    "nonlinear-functions": 211,
    "nonlinear-equations-in-one-variable-and-systems-of-equations-in-two-variables": 135,
    "linear-functions": 128,
    "linear-equations-in-two-variables": 120,
    "equivalent-expressions": 107,
    "command-of-evidence": 102,
    "systems-of-two-linear-equations-in-two-variables": 99,
    "linear-equations-in-one-variable": 94,
    "rhetorical-synthesis": 86,
    "ratios-rates-proportional-relationships-and-units": 85,
    "lines-angles-and-triangles": 84,
    "area-and-volume": 80,
    "one-variable-data-distributions-and-measures-of-center-and-spread": 77,
    "percentages": 76,
    "transitions": 75,
    "central-ideas-and-details": 74,
    "linear-inequalities-in-one-or-two-variables": 69,
    "text-structure-and-purpose": 68,
    "inferences": 61,
    "boundaries": 60,
    "two-variable-data-models-and-scatterplots": 59,
    "form-structure-and-sense": 57,
    "words-in-context": 55,
    "circles": 53,
    "right-triangles-and-trigonometry": 47,
    "probability-and-conditional-probability": 45,
    "cross-text-connections": 37,
    "inference-from-sample-statistics-and-margin-of-error": 24,
    "evaluating-statistical-claims-observational-studies-and-experiments": 11
  }
}