{
  "questionId": "cc7ffe02",
  "externalId": "a44626e2-3239-48f1-90f6-145e3b8b2c54",
  "section": "Math",
  "difficulty": "Hard",
  "difficultyCode": "H",
  "domain": "Algebra",
  "domainCode": "H",
  "skill": "Linear equations in two variables",
  "skillCode": "H.C.",
  "scoreBand": 6,
  "ibn": null,
  "updateDate": 1691007959814,
  "createDate": 1691007959814,
  "scrapedAt": "2026-05-25T12:08:04.305901+00:00",
  "type": "mcq",
  "stem": "<p style=\"text-align: left;\">Keenan made <math alttext=\"32\"><mn>32</mn>\n</math> cups of vegetable broth. Keenan then filled <math alttext=\"x\"><mi>x</mi>\n</math> small jars and <math alttext=\"y\"><mi>y</mi>\n</math> large jars with all the vegetable broth he made. The equation&nbsp;<math alttext=\"3 x plus 5 y equals 32\"><mn>3</mn><mi>x</mi><mo>+</mo><mn>5</mn><mi>y</mi><mo>=</mo><mn>32</mn></math> represents this situation. Which is the best interpretation of <math alttext=\"5 y\"><mrow>\n\t<mn>5</mn>\n\t<mi>y</mi>\n</mrow>\n</math> in this context?</p>",
  "answerOptions": [
    {
      "id": "17647838-3647-4623-b3e9-1d722518efe3",
      "content": "<p style=\"text-align: left;\">The number of large jars Keenan filled</p>"
    },
    {
      "id": "3d1d9788-235c-4a9b-b842-5d7394a33415",
      "content": "<p style=\"text-align: left;\">The number of small jars Keenan filled</p>"
    },
    {
      "id": "aabb4df7-af68-4ec5-85ca-330d0070a965",
      "content": "<p style=\"text-align: left;\">The total number of cups of vegetable broth in the large jars</p>"
    },
    {
      "id": "266b5f14-5af2-4047-924f-2334f1651374",
      "content": "<p style=\"text-align: left;\">The total number of cups of vegetable broth in the small jars</p>"
    }
  ],
  "keys": [
    "aabb4df7-af68-4ec5-85ca-330d0070a965"
  ],
  "rationale": "<p style=\"text-align: left;\">Choice C is correct. It&rsquo;s given that the equation <math alttext=\"3 x plus 5 y equals 32\"><mrow>\n\t<mrow>\n\t\t<mrow>\n\t\t\t<mn>3</mn>\n\t\t\t<mi>x</mi>\n\t\t</mrow>\n\t\t<mo>+</mo>\n\t\t<mrow>\n\t\t\t<mn>5</mn>\n\t\t\t<mi>y</mi>\n\t\t</mrow>\n\t</mrow>\n\t<mo>=</mo>\n\t<mn>32</mn>\n</mrow>\n</math> represents the situation where Keenan filled <math alttext=\"x\"><mi>x</mi>\n</math> small jars and <math alttext=\"y\"><mi>y</mi>\n</math> large jars with all the vegetable broth he made, which was <math alttext=\"32\"><mn>32</mn>\n</math> cups. Therefore, <math alttext=\"3 x\"><mrow>\n\t<mn>3</mn>\n\t<mi>x</mi>\n</mrow>\n</math> represents the total number of cups of vegetable broth in the small jars and <math alttext=\"5 y\"><mrow>\n\t<mn>5</mn>\n\t<mi>y</mi>\n</mrow>\n</math> represents the total number of cups of vegetable broth in the large jars.&nbsp;</p>\n<p>Choice A is incorrect. The number of large jars Keenan filled is represented by <math alttext=\"y\"><mi>y</mi>\n</math>, not <math alttext=\"5 y\"><mrow>\n\t<mn>5</mn>\n\t<mi>y</mi>\n</mrow>\n</math>.</p>\n<p>Choice B is incorrect. The number of small jars Keenan filled is represented by <math alttext=\"x\"><mi>x</mi>\n</math>, not <math alttext=\"5 y\"><mrow>\n\t<mn>5</mn>\n\t<mi>y</mi>\n</mrow>\n</math>.</p>\n<p>Choice D is incorrect. The total number of cups of vegetable broth in the small jars is represented by <math alttext=\"3 x\"><mrow>\n\t<mn>3</mn>\n\t<mi>x</mi>\n</mrow>\n</math>, not <math alttext=\"5 y\"><mrow>\n\t<mn>5</mn>\n\t<mi>y</mi>\n</mrow>\n</math>.&nbsp;</p>",
  "raw": {
    "keys": [
      "aabb4df7-af68-4ec5-85ca-330d0070a965"
    ],
    "rationale": "<p style=\"text-align: left;\">Choice C is correct. It&rsquo;s given that the equation <math alttext=\"3 x plus 5 y equals 32\"><mrow>\n\t<mrow>\n\t\t<mrow>\n\t\t\t<mn>3</mn>\n\t\t\t<mi>x</mi>\n\t\t</mrow>\n\t\t<mo>+</mo>\n\t\t<mrow>\n\t\t\t<mn>5</mn>\n\t\t\t<mi>y</mi>\n\t\t</mrow>\n\t</mrow>\n\t<mo>=</mo>\n\t<mn>32</mn>\n</mrow>\n</math> represents the situation where Keenan filled <math alttext=\"x\"><mi>x</mi>\n</math> small jars and <math alttext=\"y\"><mi>y</mi>\n</math> large jars with all the vegetable broth he made, which was <math alttext=\"32\"><mn>32</mn>\n</math> cups. Therefore, <math alttext=\"3 x\"><mrow>\n\t<mn>3</mn>\n\t<mi>x</mi>\n</mrow>\n</math> represents the total number of cups of vegetable broth in the small jars and <math alttext=\"5 y\"><mrow>\n\t<mn>5</mn>\n\t<mi>y</mi>\n</mrow>\n</math> represents the total number of cups of vegetable broth in the large jars.&nbsp;</p>\n<p>Choice A is incorrect. The number of large jars Keenan filled is represented by <math alttext=\"y\"><mi>y</mi>\n</math>, not <math alttext=\"5 y\"><mrow>\n\t<mn>5</mn>\n\t<mi>y</mi>\n</mrow>\n</math>.</p>\n<p>Choice B is incorrect. The number of small jars Keenan filled is represented by <math alttext=\"x\"><mi>x</mi>\n</math>, not <math alttext=\"5 y\"><mrow>\n\t<mn>5</mn>\n\t<mi>y</mi>\n</mrow>\n</math>.</p>\n<p>Choice D is incorrect. The total number of cups of vegetable broth in the small jars is represented by <math alttext=\"3 x\"><mrow>\n\t<mn>3</mn>\n\t<mi>x</mi>\n</mrow>\n</math>, not <math alttext=\"5 y\"><mrow>\n\t<mn>5</mn>\n\t<mi>y</mi>\n</mrow>\n</math>.&nbsp;</p>",
    "origin": "manifold",
    "stem": "<p style=\"text-align: left;\">Keenan made <math alttext=\"32\"><mn>32</mn>\n</math> cups of vegetable broth. Keenan then filled <math alttext=\"x\"><mi>x</mi>\n</math> small jars and <math alttext=\"y\"><mi>y</mi>\n</math> large jars with all the vegetable broth he made. The equation&nbsp;<math alttext=\"3 x plus 5 y equals 32\"><mn>3</mn><mi>x</mi><mo>+</mo><mn>5</mn><mi>y</mi><mo>=</mo><mn>32</mn></math> represents this situation. Which is the best interpretation of <math alttext=\"5 y\"><mrow>\n\t<mn>5</mn>\n\t<mi>y</mi>\n</mrow>\n</math> in this context?</p>",
    "externalid": "a44626e2-3239-48f1-90f6-145e3b8b2c54",
    "templateid": "2861306d-c7c7-4834-8afb-343a5a604f17",
    "vaultid": "f95eb4aa-f910-4683-b650-480c2996d699",
    "type": "mcq",
    "answerOptions": [
      {
        "id": "17647838-3647-4623-b3e9-1d722518efe3",
        "content": "<p style=\"text-align: left;\">The number of large jars Keenan filled</p>"
      },
      {
        "id": "3d1d9788-235c-4a9b-b842-5d7394a33415",
        "content": "<p style=\"text-align: left;\">The number of small jars Keenan filled</p>"
      },
      {
        "id": "aabb4df7-af68-4ec5-85ca-330d0070a965",
        "content": "<p style=\"text-align: left;\">The total number of cups of vegetable broth in the large jars</p>"
      },
      {
        "id": "266b5f14-5af2-4047-924f-2334f1651374",
        "content": "<p style=\"text-align: left;\">The total number of cups of vegetable broth in the small jars</p>"
      }
    ],
    "correct_answer": [
      "C"
    ]
  }
}