{
  "questionId": "5f46fc76-s1",
  "originalId": "5f46fc76",
  "setId": "set-1",
  "section": "Math",
  "difficulty": "Easy",
  "difficultyCode": "E",
  "domain": "Algebra",
  "domainCode": "H",
  "skill": "Systems of two linear equations in two variables",
  "skillCode": "H.D.",
  "type": "mcq",
  "stimulus": null,
  "stem": "<p>y = x + 3</p><p>y = -2x - 6</p><p>What is the solution (x, y) to the given system of equations?</p>",
  "answerOptions": [
    {
      "id": "a",
      "content": "<p>(0, 3)</p>"
    },
    {
      "id": "b",
      "content": "<p>(-3, 0)</p>"
    },
    {
      "id": "c",
      "content": "<p>(3, -6)</p>"
    },
    {
      "id": "d",
      "content": "<p>(-6, -3)</p>"
    }
  ],
  "keys": [
    "b"
  ],
  "rationale": "<p>Choice B is correct. Setting x + 3 = -2x - 6 yields 3x = -9, so x = -3 and y = 0.</p><p>Other choices do not satisfy both equations.</p>",
  "generatedAt": "2026-05-26T00:27:30Z",
  "templateId": "systems-of-two-linear-equations-in-two-variables.A1.T2.easy"
}