{
  "questionId": "ecf8d15f",
  "externalId": "d508e9d9-e929-4af5-bec0-719d24880e3c",
  "section": "Math",
  "difficulty": "Easy",
  "difficultyCode": "E",
  "domain": "Problem-Solving and Data Analysis",
  "domainCode": "Q",
  "skill": "Probability and conditional probability",
  "skillCode": "Q.E.",
  "scoreBand": 1,
  "ibn": "",
  "updateDate": 1776362727993,
  "createDate": 1776362727993,
  "scrapedAt": "2026-05-25T12:10:04.041995+00:00",
  "type": "mcq",
  "stem": "<p style=\"text-align: left;\">A total of <math alttext=\"50\"><mn>50</mn>\n</math> children attended a summer camp and were offered <math alttext=\"4\"><mn>4</mn>\n</math> types of sandwiches. The table shows the number of children who chose each type of sandwich.</p>\n<figure class=\"table\"><table border=\"1\">\n<thead>\n<tr style=\"height: 22px;\">\n<th style=\"width: 47.744%; height: 22px; text-align: center;\" scope=\"col\">Type of sandwich</th>\n<th style=\"width: 47.744%; height: 22px; text-align: center;\" scope=\"col\">Number of children</th>\n</tr>\n</thead>\n<tbody>\n<tr style=\"height: 22px;\">\n<td style=\"width: 47.744%; height: 22px; text-align: left;\">Turkey</td>\n<td style=\"width: 47.744%; height: 22px; text-align: center;\"><math alttext=\"15\"><mn>15</mn>\n</math></td>\n</tr>\n<tr style=\"height: 22px;\">\n<td style=\"width: 47.744%; height: 22px; text-align: left;\">Chicken</td>\n<td style=\"width: 47.744%; height: 22px; text-align: center;\"><math alttext=\"23\"><mn>23</mn>\n</math></td>\n</tr>\n<tr style=\"height: 22px;\">\n<td style=\"width: 47.744%; height: 22px; text-align: left;\">Ham</td>\n<td style=\"width: 47.744%; height: 22px; text-align: center;\"><math alttext=\"3\"><mn>3</mn>\n</math></td>\n</tr>\n<tr style=\"height: 22px;\">\n<td style=\"width: 47.744%; height: 22px; text-align: left;\">Vegetarian</td>\n<td style=\"width: 47.744%; height: 22px; text-align: center;\"><math alttext=\"9\"><mn>9</mn>\n</math></td>\n</tr>\n<tr style=\"height: 22px;\">\n<td style=\"width: 47.744%; height: 22px; text-align: center;\">Total</td>\n<td style=\"width: 47.744%; height: 22px; text-align: center;\"><math alttext=\"50\"><mn>50</mn>\n</math></td>\n</tr>\n</tbody>\n</table></figure>\n<p style=\"text-align: left;\">If one of these children is selected at random, what is the probability of selecting a child who chose a vegetarian sandwich?</p>",
  "answerOptions": [
    {
      "id": "3a4d158c-3c16-4504-b2f1-17f164d46a14",
      "content": "<p><math alttext=\"StartFraction 9 Over 100 EndFraction\"><mfrac>\n\t<mn>9</mn>\n\t<mn>100</mn>\n</mfrac>\n</math></p>"
    },
    {
      "id": "f70aa162-6088-4c26-a192-c84a1135aefd",
      "content": "<p><math alttext=\"nine fiftieths\"><mfrac>\n\t<mn>9</mn>\n\t<mn>50</mn>\n</mfrac>\n</math></p>"
    },
    {
      "id": "318a76c0-915b-49ee-ae5f-b77b31e2fe7f",
      "content": "<p><math alttext=\"one fourth\"><mfrac>\n\t<mn>1</mn>\n\t<mn>4</mn>\n</mfrac>\n</math></p>"
    },
    {
      "id": "f358b77a-b3ec-4ab5-b272-24a61521d411",
      "content": "<p><math alttext=\"nine tenths\"><mfrac>\n\t<mn>9</mn>\n\t<mn>10</mn>\n</mfrac>\n</math></p>"
    }
  ],
  "keys": [
    "f70aa162-6088-4c26-a192-c84a1135aefd"
  ],
  "rationale": "<p style=\"text-align: left;\">Choice B is correct. If one of these children is selected at random, the probability of selecting a child who chose a vegetarian sandwich is equal to the number of children who chose a vegetarian sandwich divided by the total number of children. According to the table, there are a total of&nbsp;<math xmlns=\"http://www.w3.org/1998/Math/MathML\" alttext=\"50\"><mn>50</mn></math> children, and&nbsp;<math xmlns=\"http://www.w3.org/1998/Math/MathML\" alttext=\"9\"><mn>9</mn></math> of these children chose a vegetarian sandwich. Therefore, the probability of selecting a child who chose a vegetarian sandwich is <math xmlns=\"http://www.w3.org/1998/Math/MathML\" alttext=\"nine fiftieths\"><mfrac><mn>9</mn><mn>50</mn></mfrac></math>.</p>\n<p style=\"text-align: left;\">Choice A is incorrect and may result from conceptual or calculation errors.</p>\n<p style=\"text-align: left;\">Choice C is incorrect and may result from conceptual or calculation errors.</p>\n<p style=\"text-align: left;\">Choice D is incorrect and may result from conceptual or calculation errors.</p>",
  "raw": {
    "type": "mcq",
    "stem": "<p style=\"text-align: left;\">A total of <math alttext=\"50\"><mn>50</mn>\n</math> children attended a summer camp and were offered <math alttext=\"4\"><mn>4</mn>\n</math> types of sandwiches. The table shows the number of children who chose each type of sandwich.</p>\n<figure class=\"table\"><table border=\"1\">\n<thead>\n<tr style=\"height: 22px;\">\n<th style=\"width: 47.744%; height: 22px; text-align: center;\" scope=\"col\">Type of sandwich</th>\n<th style=\"width: 47.744%; height: 22px; text-align: center;\" scope=\"col\">Number of children</th>\n</tr>\n</thead>\n<tbody>\n<tr style=\"height: 22px;\">\n<td style=\"width: 47.744%; height: 22px; text-align: left;\">Turkey</td>\n<td style=\"width: 47.744%; height: 22px; text-align: center;\"><math alttext=\"15\"><mn>15</mn>\n</math></td>\n</tr>\n<tr style=\"height: 22px;\">\n<td style=\"width: 47.744%; height: 22px; text-align: left;\">Chicken</td>\n<td style=\"width: 47.744%; height: 22px; text-align: center;\"><math alttext=\"23\"><mn>23</mn>\n</math></td>\n</tr>\n<tr style=\"height: 22px;\">\n<td style=\"width: 47.744%; height: 22px; text-align: left;\">Ham</td>\n<td style=\"width: 47.744%; height: 22px; text-align: center;\"><math alttext=\"3\"><mn>3</mn>\n</math></td>\n</tr>\n<tr style=\"height: 22px;\">\n<td style=\"width: 47.744%; height: 22px; text-align: left;\">Vegetarian</td>\n<td style=\"width: 47.744%; height: 22px; text-align: center;\"><math alttext=\"9\"><mn>9</mn>\n</math></td>\n</tr>\n<tr style=\"height: 22px;\">\n<td style=\"width: 47.744%; height: 22px; text-align: center;\">Total</td>\n<td style=\"width: 47.744%; height: 22px; text-align: center;\"><math alttext=\"50\"><mn>50</mn>\n</math></td>\n</tr>\n</tbody>\n</table></figure>\n<p style=\"text-align: left;\">If one of these children is selected at random, what is the probability of selecting a child who chose a vegetarian sandwich?</p>",
    "keys": [
      "f70aa162-6088-4c26-a192-c84a1135aefd"
    ],
    "answerOptions": [
      {
        "id": "3a4d158c-3c16-4504-b2f1-17f164d46a14",
        "content": "<p><math alttext=\"StartFraction 9 Over 100 EndFraction\"><mfrac>\n\t<mn>9</mn>\n\t<mn>100</mn>\n</mfrac>\n</math></p>"
      },
      {
        "id": "f70aa162-6088-4c26-a192-c84a1135aefd",
        "content": "<p><math alttext=\"nine fiftieths\"><mfrac>\n\t<mn>9</mn>\n\t<mn>50</mn>\n</mfrac>\n</math></p>"
      },
      {
        "id": "318a76c0-915b-49ee-ae5f-b77b31e2fe7f",
        "content": "<p><math alttext=\"one fourth\"><mfrac>\n\t<mn>1</mn>\n\t<mn>4</mn>\n</mfrac>\n</math></p>"
      },
      {
        "id": "f358b77a-b3ec-4ab5-b272-24a61521d411",
        "content": "<p><math alttext=\"nine tenths\"><mfrac>\n\t<mn>9</mn>\n\t<mn>10</mn>\n</mfrac>\n</math></p>"
      }
    ],
    "rationale": "<p style=\"text-align: left;\">Choice B is correct. If one of these children is selected at random, the probability of selecting a child who chose a vegetarian sandwich is equal to the number of children who chose a vegetarian sandwich divided by the total number of children. According to the table, there are a total of&nbsp;<math xmlns=\"http://www.w3.org/1998/Math/MathML\" alttext=\"50\"><mn>50</mn></math> children, and&nbsp;<math xmlns=\"http://www.w3.org/1998/Math/MathML\" alttext=\"9\"><mn>9</mn></math> of these children chose a vegetarian sandwich. Therefore, the probability of selecting a child who chose a vegetarian sandwich is <math xmlns=\"http://www.w3.org/1998/Math/MathML\" alttext=\"nine fiftieths\"><mfrac><mn>9</mn><mn>50</mn></mfrac></math>.</p>\n<p style=\"text-align: left;\">Choice A is incorrect and may result from conceptual or calculation errors.</p>\n<p style=\"text-align: left;\">Choice C is incorrect and may result from conceptual or calculation errors.</p>\n<p style=\"text-align: left;\">Choice D is incorrect and may result from conceptual or calculation errors.</p>",
    "externalid": "d508e9d9-e929-4af5-bec0-719d24880e3c",
    "correct_answer": [
      "B"
    ]
  }
}