{
  "questionId": "4de87c9a",
  "externalId": "d4e10666-e119-46af-8dba-a8d527aeca75",
  "section": "Math",
  "difficulty": "Easy",
  "difficultyCode": "E",
  "domain": "Algebra",
  "domainCode": "H",
  "skill": "Linear equations in one variable",
  "skillCode": "H.A.",
  "scoreBand": 2,
  "ibn": null,
  "updateDate": 1691007959808,
  "createDate": 1691007959808,
  "scrapedAt": "2026-05-25T12:08:05.197318+00:00",
  "type": "mcq",
  "stem": "<p><math alttext=\"3\"><mn>3</mn>\n</math> more than <math alttext=\"8\"><mn>8</mn>\n</math> times a number <math alttext=\"x\"><mi>x</mi>\n</math> is equal to <math alttext=\"83\"><mrow><mn>83</mn></mrow></math>. Which equation represents this situation?</p>",
  "answerOptions": [
    {
      "id": "92669f4e-a20e-4969-a618-0a2cc984a9bd",
      "content": "<p><math alttext=\"left parenthesis 3 right parenthesis left parenthesis 8 right parenthesis x equals 83\"><mo>(</mo><mrow><mn>3</mn></mrow><mo>)</mo><mo>(</mo><mrow><mn>8</mn></mrow><mo>)</mo><mi>x</mi><mo>=</mo><mrow><mn>83</mn></mrow></math></p>"
    },
    {
      "id": "430705c8-a08d-4d62-832b-42006afccf05",
      "content": "<p><math alttext=\"8 x equals 83 plus 3\"><mrow><mn>8</mn></mrow><mi>x</mi><mo>=</mo><mrow><mn>83</mn></mrow><mo>+</mo><mrow><mn>3</mn></mrow></math></p>"
    },
    {
      "id": "068f2bbc-f422-42c3-a277-21bd78977f4b",
      "content": "<p><math alttext=\"3 x plus 8 equals 83\"><mrow><mn>3</mn></mrow><mi>x</mi><mo>+</mo><mrow><mn>8</mn></mrow><mo>=</mo><mrow><mn>83</mn></mrow></math></p>"
    },
    {
      "id": "654586c4-c74f-48da-aadd-81c0b9ef9b22",
      "content": "<p><math alttext=\"8 x plus 3 equals 83\"><mrow><mn>8</mn></mrow><mi>x</mi><mo>+</mo><mrow><mn>3</mn></mrow><mo>=</mo><mrow><mn>83</mn></mrow></math></p>"
    }
  ],
  "keys": [
    "654586c4-c74f-48da-aadd-81c0b9ef9b22"
  ],
  "rationale": "<p style=\"text-align: left;\">Choice D is correct. The given phrase &ldquo;<math alttext=\"8\"><mn>8</mn>\n</math> times a number <math alttext=\"x\"><mi>x</mi>\n</math>&rdquo; can be represented by the expression <math alttext=\"8 x\"><mrow>\n\t<mn>8</mn>\n\t<mi>x</mi>\n</mrow>\n</math>. The given phrase &ldquo;<math alttext=\"3\"><mn>3</mn>\n</math> more than&rdquo; indicates an increase of <math alttext=\"3\"><mn>3</mn>\n</math> to a quantity. Therefore &ldquo;<math alttext=\"3\"><mn>3</mn>\n</math> more than <math alttext=\"8\"><mn>8</mn>\n</math> times a number <math alttext=\"x\"><mi>x</mi>\n</math>&rdquo; can be represented by the expression <math alttext=\"8 x plus 3\"><mrow>\n\t<mrow>\n\t\t<mn>8</mn>\n\t\t<mi>x</mi>\n\t</mrow>\n\t<mo>+</mo>\n\t<mn>3</mn>\n</mrow>\n</math>. Since it&rsquo;s given that <math alttext=\"3\"><mn>3</mn>\n</math> more than <math alttext=\"8\"><mn>8</mn>\n</math> times a number <math alttext=\"x\"><mi>x</mi>\n</math> is equal to <math alttext=\"83\"><mn>83</mn>\n</math>, it follows that <math alttext=\"8 x plus 3\"><mrow>\n\t<mrow>\n\t\t<mn>8</mn>\n\t\t<mi>x</mi>\n\t</mrow>\n\t<mo>+</mo>\n\t<mn>3</mn>\n</mrow>\n</math> is equal to <math alttext=\"83\"><mn>83</mn>\n</math>, or <math alttext=\"8 x plus 3 equals 83\"><mrow>\n\t<mrow>\n\t\t<mrow>\n\t\t\t<mn>8</mn>\n\t\t\t<mi>x</mi>\n\t\t</mrow>\n\t\t<mo>+</mo>\n\t\t<mn>3</mn>\n\t</mrow>\n\t<mo>=</mo>\n\t<mn>83</mn>\n</mrow>\n</math>. Therefore, the equation that represents this situation is <math alttext=\"8 x plus 3 equals 83\"><mrow>\n\t<mrow>\n\t\t<mrow>\n\t\t\t<mn>8</mn>\n\t\t\t<mi>x</mi>\n\t\t</mrow>\n\t\t<mo>+</mo>\n\t\t<mn>3</mn>\n\t</mrow>\n\t<mo>=</mo>\n\t<mn>83</mn>\n</mrow>\n</math>.</p>\n<p style=\"text-align: left;\">Choice A is incorrect. This equation represents <math alttext=\"3\"><mn>3</mn>\n</math> times the quantity <math alttext=\"8\"><mn>8</mn>\n</math> times a number <math alttext=\"x\"><mi>x</mi>\n</math> is equal to <math alttext=\"83\"><mn>83</mn>\n</math>.&nbsp;</p>\n<p style=\"text-align: left;\">Choice B is incorrect. This equation represents <math alttext=\"8\"><mn>8</mn>\n</math> times a number <math alttext=\"x\"><mi>x</mi>\n</math> is equal to <math alttext=\"3\"><mn>3</mn>\n</math> more than <math alttext=\"83\"><mn>83</mn>\n</math>.</p>\n<p style=\"text-align: left;\">Choice C is incorrect. This equation represents <math alttext=\"8\"><mn>8</mn>\n</math> more than <math alttext=\"3\"><mn>3</mn>\n</math> times a number <math alttext=\"x\"><mi>x</mi>\n</math> is equal to <math alttext=\"83\"><mn>83</mn>\n</math>.</p>",
  "raw": {
    "keys": [
      "654586c4-c74f-48da-aadd-81c0b9ef9b22"
    ],
    "rationale": "<p style=\"text-align: left;\">Choice D is correct. The given phrase &ldquo;<math alttext=\"8\"><mn>8</mn>\n</math> times a number <math alttext=\"x\"><mi>x</mi>\n</math>&rdquo; can be represented by the expression <math alttext=\"8 x\"><mrow>\n\t<mn>8</mn>\n\t<mi>x</mi>\n</mrow>\n</math>. The given phrase &ldquo;<math alttext=\"3\"><mn>3</mn>\n</math> more than&rdquo; indicates an increase of <math alttext=\"3\"><mn>3</mn>\n</math> to a quantity. Therefore &ldquo;<math alttext=\"3\"><mn>3</mn>\n</math> more than <math alttext=\"8\"><mn>8</mn>\n</math> times a number <math alttext=\"x\"><mi>x</mi>\n</math>&rdquo; can be represented by the expression <math alttext=\"8 x plus 3\"><mrow>\n\t<mrow>\n\t\t<mn>8</mn>\n\t\t<mi>x</mi>\n\t</mrow>\n\t<mo>+</mo>\n\t<mn>3</mn>\n</mrow>\n</math>. Since it&rsquo;s given that <math alttext=\"3\"><mn>3</mn>\n</math> more than <math alttext=\"8\"><mn>8</mn>\n</math> times a number <math alttext=\"x\"><mi>x</mi>\n</math> is equal to <math alttext=\"83\"><mn>83</mn>\n</math>, it follows that <math alttext=\"8 x plus 3\"><mrow>\n\t<mrow>\n\t\t<mn>8</mn>\n\t\t<mi>x</mi>\n\t</mrow>\n\t<mo>+</mo>\n\t<mn>3</mn>\n</mrow>\n</math> is equal to <math alttext=\"83\"><mn>83</mn>\n</math>, or <math alttext=\"8 x plus 3 equals 83\"><mrow>\n\t<mrow>\n\t\t<mrow>\n\t\t\t<mn>8</mn>\n\t\t\t<mi>x</mi>\n\t\t</mrow>\n\t\t<mo>+</mo>\n\t\t<mn>3</mn>\n\t</mrow>\n\t<mo>=</mo>\n\t<mn>83</mn>\n</mrow>\n</math>. Therefore, the equation that represents this situation is <math alttext=\"8 x plus 3 equals 83\"><mrow>\n\t<mrow>\n\t\t<mrow>\n\t\t\t<mn>8</mn>\n\t\t\t<mi>x</mi>\n\t\t</mrow>\n\t\t<mo>+</mo>\n\t\t<mn>3</mn>\n\t</mrow>\n\t<mo>=</mo>\n\t<mn>83</mn>\n</mrow>\n</math>.</p>\n<p style=\"text-align: left;\">Choice A is incorrect. This equation represents <math alttext=\"3\"><mn>3</mn>\n</math> times the quantity <math alttext=\"8\"><mn>8</mn>\n</math> times a number <math alttext=\"x\"><mi>x</mi>\n</math> is equal to <math alttext=\"83\"><mn>83</mn>\n</math>.&nbsp;</p>\n<p style=\"text-align: left;\">Choice B is incorrect. This equation represents <math alttext=\"8\"><mn>8</mn>\n</math> times a number <math alttext=\"x\"><mi>x</mi>\n</math> is equal to <math alttext=\"3\"><mn>3</mn>\n</math> more than <math alttext=\"83\"><mn>83</mn>\n</math>.</p>\n<p style=\"text-align: left;\">Choice C is incorrect. This equation represents <math alttext=\"8\"><mn>8</mn>\n</math> more than <math alttext=\"3\"><mn>3</mn>\n</math> times a number <math alttext=\"x\"><mi>x</mi>\n</math> is equal to <math alttext=\"83\"><mn>83</mn>\n</math>.</p>",
    "origin": "manifold",
    "stem": "<p><math alttext=\"3\"><mn>3</mn>\n</math> more than <math alttext=\"8\"><mn>8</mn>\n</math> times a number <math alttext=\"x\"><mi>x</mi>\n</math> is equal to <math alttext=\"83\"><mrow><mn>83</mn></mrow></math>. Which equation represents this situation?</p>",
    "externalid": "d4e10666-e119-46af-8dba-a8d527aeca75",
    "templateid": "b5f09136-8aae-4e6d-9b84-85cd37ef49a1",
    "vaultid": "da90cee5-bf74-4451-a15e-a45292596cb8",
    "type": "mcq",
    "answerOptions": [
      {
        "id": "92669f4e-a20e-4969-a618-0a2cc984a9bd",
        "content": "<p><math alttext=\"left parenthesis 3 right parenthesis left parenthesis 8 right parenthesis x equals 83\"><mo>(</mo><mrow><mn>3</mn></mrow><mo>)</mo><mo>(</mo><mrow><mn>8</mn></mrow><mo>)</mo><mi>x</mi><mo>=</mo><mrow><mn>83</mn></mrow></math></p>"
      },
      {
        "id": "430705c8-a08d-4d62-832b-42006afccf05",
        "content": "<p><math alttext=\"8 x equals 83 plus 3\"><mrow><mn>8</mn></mrow><mi>x</mi><mo>=</mo><mrow><mn>83</mn></mrow><mo>+</mo><mrow><mn>3</mn></mrow></math></p>"
      },
      {
        "id": "068f2bbc-f422-42c3-a277-21bd78977f4b",
        "content": "<p><math alttext=\"3 x plus 8 equals 83\"><mrow><mn>3</mn></mrow><mi>x</mi><mo>+</mo><mrow><mn>8</mn></mrow><mo>=</mo><mrow><mn>83</mn></mrow></math></p>"
      },
      {
        "id": "654586c4-c74f-48da-aadd-81c0b9ef9b22",
        "content": "<p><math alttext=\"8 x plus 3 equals 83\"><mrow><mn>8</mn></mrow><mi>x</mi><mo>+</mo><mrow><mn>3</mn></mrow><mo>=</mo><mrow><mn>83</mn></mrow></math></p>"
      }
    ],
    "correct_answer": [
      "D"
    ]
  }
}